[
    {
        "turn": 0,
        "id": "player",
        "move": {
            "id": "player",
            "type": "move",
            "payload": {
                "position": {
                    "i": 1,
                    "j": 1
                }
            }
        },
        "result": {
            "position": {
                "i": 1,
                "j": 1
            }
        }
    },
    {
        "turn": 0,
        "id": "enemy",
        "move": {
            "id": "enemy",
            "type": "move",
            "payload": {
                "position": {
                    "i": 1,
                    "j": 1
                }
            }
        },
        "result": false
    }
]